deez69420/__init__.py
deez69420/myfunctions.py
deez69420-0.1.2.dist-info/LICENSE
deez69420-0.1.2.dist-info/METADATA
deez69420-0.1.2.dist-info/WHEEL
deez69420-0.1.2.dist-info/top_level.txt
deez69420-0.1.2.dist-info/RECORD
