Metadata-Version: 2.1
Name: deez69420
Version: 0.1.2
Summary: funny:)
Author: Lawrence LOng
License: MIT
Platform: UNKNOWN
License-File: LICENSE
